pd/__init__.py
pd_alias-0.1.dist-info/METADATA
pd_alias-0.1.dist-info/WHEEL
pd_alias-0.1.dist-info/top_level.txt
pd_alias-0.1.dist-info/RECORD
